firewall2df/README.MD
firewall2df/__init__.py
firewall2df/requirements.txt
firewall2df/thirdparty.json
firewall2df-0.11.dist-info/LICENSE.rst
firewall2df-0.11.dist-info/METADATA
firewall2df-0.11.dist-info/WHEEL
firewall2df-0.11.dist-info/top_level.txt
firewall2df-0.11.dist-info/RECORD
