Metadata-Version: 2.1
Name: firewall2df
Version: 0.11
Summary: Windows firewall rules to Pandas DataFrame
Home-page: https://github.com/hansalemaos/firewall2df
Author: Johannes Fischer
Author-email: aulasparticularesdealemaosp@gmail.com
License: MIT
Keywords: firewall,windows,dataframe,pandas
Classifier: Development Status :: 4 - Beta
Classifier: Programming Language :: Python :: 3 :: Only
Classifier: Programming Language :: Python :: 3.10
Classifier: Topic :: Software Development :: Libraries :: Python Modules
Classifier: Topic :: Utilities
License-File: LICENSE.rst
Requires-Dist: pandas
